common/__init__.py
common/constant.py
common/enums.py
common/extract.py
common/filter.py
common/glue_spark_utils.py
common/hello_world.py
common/lambda_utils.py
common/load.py
common/logger.py
common/utils.py
common/validation.py
kcommon-0.0.4.dist-info/LICENSE
kcommon-0.0.4.dist-info/WHEEL
kcommon-0.0.4.dist-info/METADATA
kcommon-0.0.4.dist-info/RECORD
