Metadata-Version: 2.3
Name: kcommon
Version: 0.0.4
Summary: Sample Python Project for creating a new Python Module
Author-email: "kevin.nguyen.eng" <kevin.nguyen.eng@gmail.com>
Requires-Python: >=3.10.11
Classifier: Development Status :: 3 - Alpha
Classifier: Intended Audience :: Developers
Classifier: License :: OSI Approved :: MIT License
Classifier: Programming Language :: Python :: 3 :: Only
Classifier: Programming Language :: Python :: 3.8
Classifier: Programming Language :: Python :: 3.9
Classifier: Programming Language :: Python :: 3.10
Classifier: Programming Language :: Python :: 3.11
Requires-Dist: boto3==1.35.52 ; extra == "spark"
Requires-Dist: botocore==1.35.52 ; extra == "spark"
Requires-Dist: certifi==2024.8.30 ; extra == "spark"
Requires-Dist: charset-normalizer==3.3.2 ; extra == "spark"
Requires-Dist: et_xmlfile==2.0.0 ; extra == "spark"
Requires-Dist: idna==3.10 ; extra == "spark"
Requires-Dist: jmespath==1.0.1 ; extra == "spark"
Requires-Dist: numpy==2.1.2 ; extra == "spark"
Requires-Dist: pyspark>=3.5.3 ; extra == "spark"
Requires-Dist: pandas==2.2.3 ; extra == "spark"
Requires-Dist: pytz==2024.2 ; extra == "spark"
Requires-Dist: python-dateutil==2.9.0.post0 ; extra == "spark"
Requires-Dist: py4j==0.10.9.7 ; extra == "spark"
Requires-Dist: openpyxl==3.1.5 ; extra == "spark"
Requires-Dist: requests==2.32.3 ; extra == "spark"
Requires-Dist: s3transfer==0.10.3 ; extra == "spark"
Requires-Dist: six==1.16.0 ; extra == "spark"
Requires-Dist: tzdata==2024.2 ; extra == "spark"
Requires-Dist: urllib3==2.2.3 ; extra == "spark"
Requires-Dist: bandit[toml]==1.7.5 ; extra == "test"
Requires-Dist: black==23.3.0 ; extra == "test"
Requires-Dist: check-manifest==0.49 ; extra == "test"
Requires-Dist: flake8-bugbear==23.5.9 ; extra == "test"
Requires-Dist: flake8-docstrings ; extra == "test"
Requires-Dist: flake8-formatter_junit_xml ; extra == "test"
Requires-Dist: flake8 ; extra == "test"
Requires-Dist: flake8-pyproject ; extra == "test"
Requires-Dist: pre-commit==3.3.1 ; extra == "test"
Requires-Dist: pylint==2.17.4 ; extra == "test"
Requires-Dist: pylint_junit ; extra == "test"
Requires-Dist: pytest-cov==4.0.0 ; extra == "test"
Requires-Dist: pytest-mock<3.10.1 ; extra == "test"
Requires-Dist: pytest-runner ; extra == "test"
Requires-Dist: pytest==7.3.1 ; extra == "test"
Requires-Dist: pytest-github-actions-annotate-failures ; extra == "test"
Requires-Dist: shellcheck-py==0.9.0.2 ; extra == "test"
Project-URL: Documentation, https://github.com/kevinnguyenai/python-package-template/tree/main#readme
Project-URL: Source, https://github.com/kevinnguyenai/python-package-template
Project-URL: Tracker, https://github.com/kevinnguyenai/python-package-template/issues
Provides-Extra: spark
Provides-Extra: test
